{
  "slug": "easy-tips-to-maintain-a-perfect-pool-in-las-vegas",
  "title": "Easy Tips to Maintain a Perfect Pool in Las Vegas",
  "date": "April 3, 2022",
  "category": "",
  "author": "Clean Living Pool and Spa",
  "image": "./assets/images/blog/easy-tips-to-maintain-a-perfect-pool-in-las-vegas.webp",
  "excerpt": "A swimming pool in Las Vegas is an amazing amenity, but requires proper maintenance to ensure health and safety. This guide provides seven easy tips for keeping your pool in perfect condition.",
  "body": "<p><strong>A swimming pool in Las Vegas</strong> is one of the most amazing amenities you would want to have...especially in a hot environment.</p><p>Some of the health risks that may be associated with poor pool maintenance are water borne diseases, physical injuries due to broken tiles, muck and bad aesthetics.</p><p>In order to avoid such risks and problems, you should invest in proper pool maintenance. A clean swimming pool ensures overall health of the swimmers and captures their attention.</p><p>If you own a <strong>pool in Las Vegas</strong>, you should have a complete plan to maintain it. With these tips you are certain that your swimming pool will look spick and span.</p><h2>The following are easy tips that can help you maintain a perfect pool in Las Vegas.</h2><ol><li>Maintain a weekly pool service routine for your swimming pool.</li><li>Ensure there are pool repair services.</li><li>Spearhead pool consulting services.</li><li>Always test the amounts of Chlorine in the pools</li><li>Use test kits to maintain and check the water balance.</li><li>Secure the pool properly for winter.</li><li>Always power wash your pool deck.</li></ol><h3>Tip No. 1: Maintain a weekly pool service routine.</h3><p>A weekly pool service routine can ensure the elimination of debris that floats in the swimming pool. Debris may include leaves, paper, fruit peels, and polythene items.</p><p>This skimming process is the cleaning and removal of debris from the pool on a daily basis.</p><p>This will eventually eliminate or avoid blockages in the swimming pool, thus affecting the outlet. It also helps in the water mass circulation in and out of the pool.</p><p>Brushing the sediments on the pool walls is mandatory to maintain your swimming pool. Through this you will be eliminating awful and unpleasant smells.</p><p>When you vacuum the pool, you increase the chances of removing the sediments and algae brushed from the walls from the bottom of the pool.</p><h3>Tip No. 2: Ensure there are pool repair services.</h3><p>The swimming pool repair services are among the most important services that need to be taken in. Repairs such as broken tiles need to be fixed to avoid any injuries to swimmers.</p><p>Other repair services such as heaters and heat pumps need to be replaced. In Las Vegas, temperatures may sometimes vary, leading to faulty heat pumps in the swimming pools. They regulate the waters so that it may be either warm or cold, depending on your preference. Replacements of filters are used to ensure no harmful substances get into the pool.</p><h3>Tip No. 3: Spearhead pool consultation services.</h3><p>Swimming consultation services are a tip that helps you maintain a perfect pool. You can undoubtedly inquire lots of questions on how to maintain your pool from the professionals.</p><p>Do not forget that specialists help in opinion advice that may assist in your pool management. It can also lead to new ideas from time to time.</p><p>Whether you are looking for pool renovation or construction, their services come in handy.</p><h3>Tip No. 4: Always test the amount of Chlorine in your pool.</h3><p>Chlorine is one of the chemicals we use to balance water PH in swimming pools. It is used as a management feature to safely purify and kill bacteria in the water.</p><p>You may find some amounts of Chlorine in most swimming pools, but the disadvantage is that it may lead to skin itchiness, dryness, and irritation when used in excess amounts. keeping a close watch on the amounts of chlorine in the water.</p><p>Testing the amounts of Chlorine in swimming pools is a way of securing and protecting your loved ones to avoid external uncertainties.</p><p>After testing the amounts of Chlorine in the water, be sure to leave it at normal levels. The Chlorine added to the swimming pools is also sometimes used to kill the algae's dominance in the pools.</p><p>Whenever the amounts are high, you can heat the swimming pool water till it boils using the heat pumps. Through this, you will be able to reduce the levels of Chlorine.</p><h3>Tip No. 5: Use test kits to maintain and check water balance.</h3><p>As the warm weather begins, it's swimming season. This then means that you need to check your water quality. The tests will test four principle indicators.</p><p>These tests are what the Las Vegas homeowners need for sure. Through this, you get to ensure that the salt levels (if you have a saltwater pool), phosphates, and Chlorine are at normal levels.</p><h3>Tip No. 6: Secure the pool properly for winter.</h3><p>Maintaining a pool during summer is important, but it is more crucial during winter. After all, you do not want to remove your pool cover when winter is over and find the pool full of dangerous bacteria.</p><p>When you secure your pool correctly before winter, you will save lots of time and money that would go into repairs in the next season. Be sure to invest in a proper cover to prevent the entry of debris.</p><h3>Tip No. 7: Always power wash your pool deck.</h3><p>Aside from maintaining your pool, it is also vital to ensure that the area around your pool is kept clean. Power washing the pool deck removes dust and any weather stains that occur with time.</p><p>Begin the process by first sweeping any twigs and leaves out of the pool deck. Remember to overlap the areas you have already cleaned so that no streaks will be seen.</p><h2>Seek Professional Pool Maintenance Services</h2><p>Despite having all these tips for maintaining a perfect pool, it might be a daunting task to do it yourself. In some cases, you may make the situation worse than it was.</p><p>To avoid any mishap, consult pool maintenance professionals and have an expert examine your pool to give it the perfect look it deserves.</p><p><a href=\"https://www.cleanlivingpoolandspa.com/pool-cleaning-service-las-vegas\">Clean Living Pool and Spa</a> are always ready to help. They specialize in pool maintenance in the Las Vegas area, and they will provide value for your money.</p><p>They are experts in acid wash, filter cleaning, tile cleaning, and many more. What are you waiting for? Call them now on<strong>(702) 539-3927.</strong></p>",
  "link": "./article/easy-tips-to-maintain-a-perfect-pool-in-las-vegas/"
}
