{
  "slug": "navigating-las-vegas-pool-regulations-how-to-ensure-your-pool-complies",
  "title": "Navigating Las Vegas Pool Regulations: How to Ensure Your Pool Complies",
  "date": "May 22, 2024",
  "category": "",
  "author": "Clean Living Pool and Spa",
  "image": "./assets/images/blog/navigating-las-vegas-pool-regulations-how-to-ensure-your-pool-complies.webp",
  "excerpt": "Las Vegas pool ownership requires compliance with local regulations covering safety, water quality, and environmental standards. This guide helps pool owners understand essential requirements for permits, inspections, and conservation.",
  "body": "<h2>How to Stay Compliant with Las Vegas Pool Regulations</h2><p>Las Vegas, the city that thrives in the heart of the desert, is synonymous with luxury living and lavish backyard pools. However, owning a pool in this vibrant city comes with its set of regulations designed to ensure safety and environmental compliance. Whether you're dreaming of installing a new pool or ensuring your existing oasis meets local laws, navigating Las Vegas pool regulations can seem daunting. Fear not, as this guide will walk you through the essentials, helping you enjoy the cool blue waters worry-free.</p><h2>Understanding the Basics of Pool Compliance</h2><p>Before you dive into the deep end, it's crucial to familiarize yourself with the basic requirements set forth by the City of Las Vegas. From safety barriers to water quality, these regulations are in place to protect both the pool owner and the community at large.</p><h2>Ensuring Your Pool's Safety Features Are Up to Code</h2><p>Safety barriers, alarms, and drain covers are just a few components scrutinized during a compliance inspection. Learn how to ensure your pool's safety features not only meet local standards but also offer peace of mind.</p><h2>Water Quality and Maintenance: Keeping Your Pool Clean and Clear</h2><p>Maintaining crystal-clear water isn't just about aesthetics; it's a health requirement. Discover the regulations surrounding chemical levels, filtration systems, and regular maintenance schedules to keep your pool inviting and safe for everyone.</p><h2>Navigating Permits and Inspections</h2><p>Whether you're installing a new pool or renovating an existing one, navigating the permit process is a critical step. This section will guide you through obtaining the necessary approvals and preparing for inspections.</p><h2>Environmental Considerations: Water Usage and Conservation</h2><p>In a city like Las Vegas, where water is a precious commodity, understanding water usage and conservation regulations is essential. Learn how to design and operate your pool in an eco-friendly manner, aligning with the city's efforts to conserve water.</p><p>Owning a pool in Las Vegas is a luxury that comes with its share of responsibilities. By ensuring your pool complies with local regulations, you're not just adhering to the law; you're contributing to the safety and well-being of your community. Dive into compliance with confidence, knowing that your Las Vegas pool is a safe, clean, and lawful addition to your desert oasis.</p>",
  "link": "./article/navigating-las-vegas-pool-regulations-how-to-ensure-your-pool-complies/"
}
